melopero_vl53l1x/VL53L1X.py
melopero_vl53l1x/__init__.py
melopero_vl53l1x-0.1.4.dist-info/METADATA
melopero_vl53l1x-0.1.4.dist-info/RECORD
melopero_vl53l1x-0.1.4.dist-info/WHEEL
melopero_vl53l1x-0.1.4.dist-info/top_level.txt
