Metadata-Version: 2.1
Name: melopero-vl53l1x
Version: 0.1.4
Summary: A module to easily access Melopero's VL53L1X sensor's features
Home-page: https://github.com/melopero/Melopero_VL53L1X/tree/master/module
Author: Melopero
Author-email: info@melopero.com
License: MIT
Platform: UNKNOWN
Classifier: Development Status :: 3 - Alpha
Classifier: License :: OSI Approved :: MIT License
Classifier: Programming Language :: Python :: 3
Classifier: Programming Language :: Python :: 3.5
